abraia/__init__.py
abraia/client.py
abraia/config.py
abraia/editing/__init__.py
abraia/editing/center.jpg
abraia/editing/inpaint.py
abraia/editing/removebg.py
abraia/editing/sam.py
abraia/editing/smartcrop.py
abraia/editing/upscale.py
abraia/inference/__init__.py
abraia/inference/detect.py
abraia/inference/faces.py
abraia/inference/ocr.py
abraia/inference/ops.py
abraia/inference/plates.py
abraia/inference/tools.py
abraia/inference/tracker.py
abraia/inference/clip/__init__.py
abraia/inference/clip/bpe_simple_vocab_16e6.txt.gz
abraia/inference/clip/preprocessor.py
abraia/inference/clip/tokenizer.py
abraia/multiple/__init__.py
abraia/multiple/hsi.py
abraia/training/__init__.py
abraia/training/classify.py
abraia/training/dataset.py
abraia/training/detect.py
abraia/utils/__init__.py
abraia/utils/compress.py
abraia/utils/draw.py
abraia/utils/sketcher.py
abraia/utils/video.py
abraia-0.25.4.data/scripts/abraia
abraia-0.25.4.data/scripts/abraia.bat
abraia-0.25.4.dist-info/LICENSE
abraia-0.25.4.dist-info/METADATA
abraia-0.25.4.dist-info/WHEEL
abraia-0.25.4.dist-info/top_level.txt
abraia-0.25.4.dist-info/RECORD
