Metadata-Version: 2.1
Name: abraia
Version: 0.25.4
Summary: Abraia Python SDK
Home-page: https://github.com/abraia/abraia-multiple
Author: Jorge Rodriguez Araujo
Author-email: jorge@abraiasoftware.com
License: MIT
Platform: UNKNOWN
Requires-Dist: click>=8.0.3
Requires-Dist: numpy>=1.21.0
Requires-Dist: Pillow>=8.0.0
Requires-Dist: filetype>=1.0.7
Requires-Dist: onnxruntime>=1.18.1
Requires-Dist: opencv-python-headless>=4.10.0.84
Requires-Dist: python-dotenv>=0.21.1
Requires-Dist: requests>=2.27.1
Requires-Dist: tqdm>=4.62.3
Requires-Dist: ftfy>=6.2.3
Requires-Dist: lap>=0.5.12
Requires-Dist: regex>=2024.11.6
Provides-Extra: dev
Requires-Dist: opencv-python>=4.10.0.84; extra == "dev"
Requires-Dist: ImageHash>=4.3.2; extra == "dev"
Requires-Dist: tifffile>=2024.8.30; extra == "dev"
Requires-Dist: ultralytics>=8.3.161; extra == "dev"
Requires-Dist: onnx>=1.18.0; extra == "dev"
Requires-Dist: transformers>=4.57.1; extra == "dev"
Provides-Extra: multiple
Requires-Dist: spectral>=0.23.1; extra == "multiple"
Requires-Dist: scipy>=1.14.1; extra == "multiple"
Requires-Dist: tifffile>=2024.8.30; extra == "multiple"
